pysoundcard.py
PySoundCard-0.5.2.dist-info/DESCRIPTION.rst
PySoundCard-0.5.2.dist-info/METADATA
PySoundCard-0.5.2.dist-info/RECORD
PySoundCard-0.5.2.dist-info/WHEEL
PySoundCard-0.5.2.dist-info/metadata.json
PySoundCard-0.5.2.dist-info/top_level.txt
