Metadata-Version: 1.1
Name: PySoundCard
Version: 0.5.2
Summary: An audio library based on PortAudio, CFFI and NumPy
Home-page: https://github.com/bastibe/PySoundCard
Author: Bastian Bechtold
Author-email: basti@bastibe.de
License: BSD 3-Clause License
Keywords: audio,portaudio
Platform: any
Classifier: Development Status :: 3 - Alpha
Classifier: Environment :: Other Environment
Classifier: Intended Audience :: Developers
Classifier: Intended Audience :: Science/Research
Classifier: License :: OSI Approved :: BSD License
Classifier: Natural Language :: English
Classifier: Operating System :: OS Independent
Classifier: Programming Language :: Python
Classifier: Programming Language :: Python :: 3
Classifier: Programming Language :: Python :: Implementation :: PyPy
Classifier: Topic :: Multimedia :: Sound/Audio
